{"totalPageViews":6131,"totalSessions":1067,"dailyStats":[{"date":"2026-03-22","pageViews":258,"sessions":239,"uniqueIPs":0,"bounceCount":229,"avgDurationSec":10},{"date":"2026-03-21","pageViews":228,"sessions":171,"uniqueIPs":0,"bounceCount":146,"avgDurationSec":62},{"date":"2026-03-20","pageViews":524,"sessions":148,"uniqueIPs":0,"bounceCount":106,"avgDurationSec":89},{"date":"2026-03-19","pageViews":370,"sessions":223,"uniqueIPs":0,"bounceCount":179,"avgDurationSec":64},{"date":"2026-03-18","pageViews":4731,"sessions":279,"uniqueIPs":0,"bounceCount":159,"avgDurationSec":660},{"date":"2026-03-17","pageViews":20,"sessions":7,"uniqueIPs":0,"bounceCount":5,"avgDurationSec":143}],"pageStats":{"/":{"views":2608,"exits":831,"totalDwellSec":41837,"bounces":772},"/story":{"views":207,"exits":3,"totalDwellSec":2240,"bounces":2},"/menu":{"views":168,"exits":17,"totalDwellSec":6059,"bounces":0},"/franchise":{"views":286,"exits":38,"totalDwellSec":7384,"bounces":8},"/stores":{"views":255,"exits":8,"totalDwellSec":3165,"bounces":0},"/franchise/inquiry":{"views":4,"exits":3,"totalDwellSec":21,"bounces":3},"/franchise/conversion":{"views":296,"exits":2,"totalDwellSec":51827,"bounces":1},"/privacy":{"views":64,"exits":0,"totalDwellSec":128,"bounces":0},"/order":{"views":564,"exits":7,"totalDwellSec":941,"bounces":3},"/order/cheongju":{"views":968,"exits":104,"totalDwellSec":69099,"bounces":33},"/order/cheongju/cart":{"views":403,"exits":25,"totalDwellSec":24301,"bounces":1},"/order/cheongju/complete":{"views":152,"exits":27,"totalDwellSec":9694,"bounces":1},"/order/yeouido":{"views":81,"exits":0,"totalDwellSec":190,"bounces":0},"/order/gongdeok":{"views":49,"exits":0,"totalDwellSec":98,"bounces":0},"/orders":{"views":19,"exits":1,"totalDwellSec":76,"bounces":0},"/franchise/landing":{"views":2,"exits":0,"totalDwellSec":34,"bounces":0},"/customer":{"views":1,"exits":0,"totalDwellSec":20,"bounces":0},"/franchise/process":{"views":2,"exits":1,"totalDwellSec":7,"bounces":0},"/franchise/cost":{"views":2,"exits":0,"totalDwellSec":42,"bounces":0}}}